rtl/program_counter.v
module program_counter (
    input wire clk,          // Clock input
    input wire rst_n,        // Active low reset
    input wire pc_write,     // Enable signal
    input wire [31:0] next_pc, // Next program counter value
    output reg [31:0] pc_out   // Current program counter value
);

    // Sequential logic for program counter
    always @(posedge clk or negedge rst_n) begin
        if (!rst_n) begin
            pc_out <= 32'h0;  // Reset to address 0
        end else if (pc_write) begin
            pc_out <= next_pc;
        end
    end

endmodule

testbench/program_counter_tb.v
module program_counter_tb;
    // Testbench signals
    reg clk;
    reg rst_n;
    reg pc_write;
    reg [31:0] next_pc;
    wire [31:0] pc_out;

    // Instantiate the program counter
    program_counter pc_inst (
        .clk(clk),
        .rst_n(rst_n),
        .pc_write(pc_write),
        .next_pc(next_pc),
        .pc_out(pc_out)
    );

    // Clock generation
    always begin
        #5 clk = ~clk;  // 100MHz clock
    end

    // Test stimulus
    initial begin
        // Initialize waveform dumping
        $dumpfile("program_counter.vcd");
        $dumpvars(0, program_counter_tb);

        // Initialize signals
        clk = 0;
        rst_n = 1;
        pc_write = 0;
        next_pc = 32'h0;

        // Test 1: Reset
        #10 rst_n = 0;
        #10 rst_n = 1;

        // Test 2: Normal increment
        #10;
        pc_write = 1;
        next_pc = 32'h4;
        #10;
        next_pc = 32'h8;
        #10;
        next_pc = 32'hC;

        // Test 3: Jump
        #10;
        next_pc = 32'h1000;
        #10;

        // Test 4: Disable writes
        pc_write = 0;
        next_pc = 32'h1004;
        #20;

        // Test 5: Re-enable writes
        pc_write = 1;
        #10;

        // End simulation
        #10;
        $display("All tests completed!");
        $finish;
    end

    // Monitor changes
    always @(posedge clk) begin
        $display("Time=%0t rst_n=%0b pc_write=%0b next_pc=%0h pc_out=%0h",
                 $time, rst_n, pc_write, next_pc, pc_out);
    end

endmodule

program_counter.vcd
$date
	Sun Apr 13 15:34:00 2025
$end
$version
	Icarus Verilog
$end
$timescale
	1s
$end
$scope module program_counter_tb $end
$var wire 32 ! pc_out [31:0] $end
$var reg 1 " clk $end
$var reg 32 # next_pc [31:0] $end
$var reg 1 $ pc_write $end
$var reg 1 % rst_n $end
$scope module pc_inst $end
$var wire 1 " clk $end
$var wire 32 & next_pc [31:0] $end
$var wire 1 $ pc_write $end
$var wire 1 % rst_n $end
$var reg 32 ' pc_out [31:0] $end
$upscope $end
$upscope $end
$enddefinitions $end
$comment Show the parameter values. $end
$dumpall
$end
#0
$dumpvars
bx '
b0 &
1%
0$
b0 #
0"
bx !
$end
#5
1"
#10
b0 !
b0 '
0"
0%
#15
1"
#20
0"
1%
#25
1"
#30
0"
b100 #
b100 &
1$
#35
b100 !
b100 '
1"
#40
0"
b1000 #
b1000 &
#45
b1000 !
b1000 '
1"
#50
0"
b1100 #
b1100 &
#55
b1100 !
b1100 '
1"
#60
0"
b1000000000000 #
b1000000000000 &
#65
b1000000000000 !
b1000000000000 '
1"
#70
0"
b1000000000100 #
b1000000000100 &
0$
#75
1"
#80
0"
#85
1"
#90
0"
1$
#95
b1000000000100 !
b1000000000100 '
1"
