rtl/alu.v
module alu (
    input wire [31:0] op_a,
    input wire [31:0] op_b,
    input wire [3:0] alu_ctrl,
    output reg [31:0] result,
    output wire zero,
    output reg overflow
);

    // ALU Control codes
    localparam ALU_ADD  = 4'b0000;
    localparam ALU_SUB  = 4'b0001;
    localparam ALU_AND  = 4'b0010;
    localparam ALU_OR   = 4'b0011;
    localparam ALU_XOR  = 4'b0100;
    localparam ALU_SLT  = 4'b0101;
    localparam ALU_SLL  = 4'b0110;
    localparam ALU_SRL  = 4'b0111;
    localparam ALU_SRA  = 4'b1000;

    // Zero flag
    assign zero = (result == 32'b0);

    // Main ALU operation
    always @(*) begin
        // Default no overflow
        overflow = 1'b0;
        
        case (alu_ctrl)
            ALU_ADD: begin
                {overflow, result} = {op_a[31], op_a} + {op_b[31], op_b};
            end
            
            ALU_SUB: begin
                {overflow, result} = {op_a[31], op_a} - {op_b[31], op_b};
            end
            
            ALU_AND: begin
                result = op_a & op_b;
            end
            
            ALU_OR: begin
                result = op_a | op_b;
            end
            
            ALU_XOR: begin
                result = op_a ^ op_b;
            end
            
            ALU_SLT: begin
                result = ($signed(op_a) < $signed(op_b)) ? 32'b1 : 32'b0;
            end
            
            ALU_SLL: begin
                result = op_a << op_b[4:0];
            end
            
            ALU_SRL: begin
                result = op_a >> op_b[4:0];
            end
            
            ALU_SRA: begin
                result = $signed(op_a) >>> op_b[4:0];
            end
            
            default: begin
                result = 32'b0;
                overflow = 1'b0;
            end
        endcase
    end

endmodule

testbench/alu_tb.v
module alu_tb;
    // Testbench signals
    reg [31:0] op_a;
    reg [31:0] op_b;
    reg [3:0] alu_ctrl;
    wire [31:0] result;
    wire zero;
    wire overflow;

    // Instantiate the ALU
    alu alu_inst (
        .op_a(op_a),
        .op_b(op_b),
        .alu_ctrl(alu_ctrl),
        .result(result),
        .zero(zero),
        .overflow(overflow)
    );

    // Test stimulus
    initial begin
        // Initialize waveform dumping
        $dumpfile("sim/alu.vcd");
        $dumpvars(0, alu_tb);

        // Test 1: Addition
        op_a = 32'h00000005;
        op_b = 32'h00000003;
        alu_ctrl = 4'b0000;  // ADD
        #10;
        
        // Test overflow
        op_a = 32'h7FFFFFFF;
        op_b = 32'h00000001;
        #10;

        // Test 2: Subtraction
        op_a = 32'h00000005;
        op_b = 32'h00000003;
        alu_ctrl = 4'b0001;  // SUB
        #10;

        // Test 3: AND
        op_a = 32'hFF00FF00;
        op_b = 32'h0F0F0F0F;
        alu_ctrl = 4'b0010;  // AND
        #10;

        // Test 4: OR
        op_a = 32'hFF00FF00;
        op_b = 32'h0F0F0F0F;
        alu_ctrl = 4'b0011;  // OR
        #10;

        // Test 5: XOR
        op_a = 32'hFF00FF00;
        op_b = 32'h0F0F0F0F;
        alu_ctrl = 4'b0100;  // XOR
        #10;

        // Test 6: SLT (Less than)
        op_a = 32'hFFFFFFFF;  // -1
        op_b = 32'h00000001;  // 1
        alu_ctrl = 4'b0101;  // SLT
        #10;

        // Test 7: Shift left logical
        op_a = 32'h00000001;
        op_b = 32'h00000004;
        alu_ctrl = 4'b0110;  // SLL
        #10;

        // Test 8: Shift right logical
        op_a = 32'h80000000;
        op_b = 32'h00000004;
        alu_ctrl = 4'b0111;  // SRL
        #10;

        // Test 9: Shift right arithmetic
        op_a = 32'h80000000;
        op_b = 32'h00000004;
        alu_ctrl = 4'b1000;  // SRA
        #10;

        // Test 10: Zero flag
        op_a = 32'h00000000;
        op_b = 32'h00000000;
        alu_ctrl = 4'b0000;  // ADD
        #10;

        // End simulation
        $display("All tests completed!");
        $finish;
    end

    // Monitor changes
    always @(*) begin
        #1; // Small delay to let signals settle
        $display("Time=%0t op_a=%0h op_b=%0h alu_ctrl=%0h result=%0h zero=%0b overflow=%0b",
                 $time, op_a, op_b, alu_ctrl, result, zero, overflow);
    end

endmodule

sim/alu.vcd
$date
	Sun Apr 13 15:40:51 2025
$end
$version
	Icarus Verilog
$end
$timescale
	1s
$end
$scope module alu_tb $end
$var wire 1 ! zero $end
$var wire 32 " result [31:0] $end
$var wire 1 # overflow $end
$var reg 4 $ alu_ctrl [3:0] $end
$var reg 32 % op_a [31:0] $end
$var reg 32 & op_b [31:0] $end
$scope module alu_inst $end
$var wire 4 ' alu_ctrl [3:0] $end
$var wire 32 ( op_a [31:0] $end
$var wire 32 ) op_b [31:0] $end
$var wire 1 ! zero $end
$var parameter 4 * ALU_ADD $end
$var parameter 4 + ALU_AND $end
$var parameter 4 , ALU_OR $end
$var parameter 4 - ALU_SLL $end
$var parameter 4 . ALU_SLT $end
$var parameter 4 / ALU_SRA $end
$var parameter 4 0 ALU_SRL $end
$var parameter 4 1 ALU_SUB $end
$var parameter 4 2 ALU_XOR $end
$var reg 1 # overflow $end
$var reg 32 3 result [31:0] $end
$upscope $end
$upscope $end
$enddefinitions $end
$comment Show the parameter values. $end
$dumpall
b100 2
b1 1
b111 0
b1000 /
b101 .
b110 -
b11 ,
b10 +
b0 *
$end
#0
$dumpvars
b1000 3
b11 )
b101 (
b0 '
b11 &
b101 %
b0 $
0#
b1000 "
0!
$end
#10
b10000000000000000000000000000000 "
b10000000000000000000000000000000 3
b1 &
b1 )
b1111111111111111111111111111111 %
b1111111111111111111111111111111 (
#20
b10 "
b10 3
b1 $
b1 '
b11 &
b11 )
b101 %
b101 (
#30
b1111000000000000111100000000 "
b1111000000000000111100000000 3
b10 $
b10 '
b1111000011110000111100001111 &
b1111000011110000111100001111 )
b11111111000000001111111100000000 %
b11111111000000001111111100000000 (
#40
b11111111000011111111111100001111 "
b11111111000011111111111100001111 3
b11 $
b11 '
#50
b11110000000011111111000000001111 "
b11110000000011111111000000001111 3
b100 $
b100 '
#60
b1 "
b1 3
b101 $
b101 '
b1 &
b1 )
b11111111111111111111111111111111 %
b11111111111111111111111111111111 (
#70
b10000 "
b10000 3
b110 $
b110 '
b100 &
b100 )
b1 %
b1 (
#80
b1000000000000000000000000000 "
b1000000000000000000000000000 3
b111 $
b111 '
b10000000000000000000000000000000 %
b10000000000000000000000000000000 (
#90
b11111000000000000000000000000000 "
b11111000000000000000000000000000 3
b1000 $
b1000 '
#100
1!
b0 "
b0 3
b0 $
b0 '
b0 &
b0 )
b0 %
b0 (
