rtl/alu_control.v
module alu_control (
    input wire [1:0] alu_op,      // ALU operation type from main control
    input wire [2:0] funct3,      // Function field 3
    input wire [6:0] funct7,      // Function field 7
    output reg [3:0] alu_ctrl     // ALU control signal
);

    // ALU operation types from main control
    localparam ALU_OP_R_TYPE = 2'b10;   // R-type operations
    localparam ALU_OP_I_TYPE = 2'b11;   // I-type operations
    localparam ALU_OP_BRANCH = 2'b01;   // Branch operations
    localparam ALU_OP_OTHER  = 2'b00;   // Other operations

    // ALU control codes
    localparam ALU_ADD  = 4'b0000;
    localparam ALU_SUB  = 4'b0001;
    localparam ALU_AND  = 4'b0010;
    localparam ALU_OR   = 4'b0011;
    localparam ALU_XOR  = 4'b0100;
    localparam ALU_SLT  = 4'b0101;
    localparam ALU_SLL  = 4'b0110;
    localparam ALU_SRL  = 4'b0111;
    localparam ALU_SRA  = 4'b1000;

    // Main ALU control logic
    always @(*) begin
        case (alu_op)
            ALU_OP_R_TYPE: begin
                case ({funct7[5], funct3})
                    4'b0000: alu_ctrl = ALU_ADD;  // add
                    4'b1000: alu_ctrl = ALU_SUB;  // sub
                    4'b0111: alu_ctrl = ALU_AND;  // and
                    4'b0110: alu_ctrl = ALU_OR;   // or
                    4'b0100: alu_ctrl = ALU_XOR;  // xor
                    4'b0010: alu_ctrl = ALU_SLT;  // slt
                    4'b0001: alu_ctrl = ALU_SLL;  // sll
                    4'b0101: alu_ctrl = ALU_SRL;  // srl
                    4'b1101: alu_ctrl = ALU_SRA;  // sra
                    default: alu_ctrl = ALU_ADD;  // default to add
                endcase
            end

            ALU_OP_I_TYPE: begin
                case (funct3)
                    3'b000: alu_ctrl = ALU_ADD;  // addi
                    3'b111: alu_ctrl = ALU_AND;  // andi
                    3'b110: alu_ctrl = ALU_OR;   // ori
                    3'b100: alu_ctrl = ALU_XOR;  // xori
                    3'b010: alu_ctrl = ALU_SLT;  // slti
                    3'b001: alu_ctrl = ALU_SLL;  // slli
                    3'b101: alu_ctrl = (funct7[5] ? ALU_SRA : ALU_SRL);  // srli/srai
                    default: alu_ctrl = ALU_ADD;  // default to addi
                endcase
            end

            ALU_OP_BRANCH: begin
                case (funct3)
                    3'b000: alu_ctrl = ALU_SUB;  // beq
                    3'b001: alu_ctrl = ALU_SUB;  // bne
                    3'b100: alu_ctrl = ALU_SLT;  // blt
                    3'b101: alu_ctrl = ALU_SLT;  // bge
                    3'b110: alu_ctrl = ALU_SLT;  // bltu
                    3'b111: alu_ctrl = ALU_SLT;  // bgeu
                    default: alu_ctrl = ALU_SUB;  // default to beq
                endcase
            end

            default: begin
                alu_ctrl = ALU_ADD;  // default to add
            end
        endcase
    end

endmodule

testbench/alu_control_tb.v
module alu_control_tb;
    // Testbench signals
    reg [1:0] alu_op;
    reg [2:0] funct3;
    reg [6:0] funct7;
    wire [3:0] alu_ctrl;

    // Instantiate the ALU control unit
    alu_control alu_ctrl_inst (
        .alu_op(alu_op),
        .funct3(funct3),
        .funct7(funct7),
        .alu_ctrl(alu_ctrl)
    );

    // Test stimulus
    initial begin
        // Initialize waveform dumping
        $dumpfile("sim/alu_control.vcd");
        $dumpvars(0, alu_control_tb);

        // Test 1: R-type instructions
        alu_op = 2'b10;  // R-type
        // add
        funct3 = 3'b000;
        funct7 = 7'b0000000;
        #10;
        // sub
        funct3 = 3'b000;
        funct7 = 7'b0100000;
        #10;
        // and
        funct3 = 3'b111;
        funct7 = 7'b0000000;
        #10;
        // or
        funct3 = 3'b110;
        funct7 = 7'b0000000;
        #10;
        // xor
        funct3 = 3'b100;
        funct7 = 7'b0000000;
        #10;
        // slt
        funct3 = 3'b010;
        funct7 = 7'b0000000;
        #10;
        // sll
        funct3 = 3'b001;
        funct7 = 7'b0000000;
        #10;
        // srl
        funct3 = 3'b101;
        funct7 = 7'b0000000;
        #10;
        // sra
        funct3 = 3'b101;
        funct7 = 7'b0100000;
        #10;

        // Test 2: I-type instructions
        alu_op = 2'b11;  // I-type
        // addi
        funct3 = 3'b000;
        funct7 = 7'b0000000;
        #10;
        // andi
        funct3 = 3'b111;
        funct7 = 7'b0000000;
        #10;
        // ori
        funct3 = 3'b110;
        funct7 = 7'b0000000;
        #10;
        // xori
        funct3 = 3'b100;
        funct7 = 7'b0000000;
        #10;
        // slti
        funct3 = 3'b010;
        funct7 = 7'b0000000;
        #10;
        // slli
        funct3 = 3'b001;
        funct7 = 7'b0000000;
        #10;
        // srli
        funct3 = 3'b101;
        funct7 = 7'b0000000;
        #10;
        // srai
        funct3 = 3'b101;
        funct7 = 7'b0100000;
        #10;

        // Test 3: Branch instructions
        alu_op = 2'b01;  // Branch
        // beq
        funct3 = 3'b000;
        funct7 = 7'b0000000;
        #10;
        // bne
        funct3 = 3'b001;
        funct7 = 7'b0000000;
        #10;
        // blt
        funct3 = 3'b100;
        funct7 = 7'b0000000;
        #10;
        // bge
        funct3 = 3'b101;
        funct7 = 7'b0000000;
        #10;
        // bltu
        funct3 = 3'b110;
        funct7 = 7'b0000000;
        #10;
        // bgeu
        funct3 = 3'b111;
        funct7 = 7'b0000000;
        #10;

        // Test 4: Other operations
        alu_op = 2'b00;  // Other
        funct3 = 3'b000;
        funct7 = 7'b0000000;
        #10;

        // End simulation
        $display("All tests completed!");
        $finish;
    end

    // Monitor changes
    always @(*) begin
        #1; // Small delay to let signals settle
        $display("Time=%0t alu_op=%0b funct3=%0b funct7=%0b alu_ctrl=%0b",
                 $time, alu_op, funct3, funct7, alu_ctrl);
    end

endmodule

sim/alu_control.vcd
$date
	Sun Apr 13 15:43:14 2025
$end
$version
	Icarus Verilog
$end
$timescale
	1s
$end
$scope module alu_control_tb $end
$var wire 4 ! alu_ctrl [3:0] $end
$var reg 2 " alu_op [1:0] $end
$var reg 3 # funct3 [2:0] $end
$var reg 7 $ funct7 [6:0] $end
$scope module alu_ctrl_inst $end
$var wire 2 % alu_op [1:0] $end
$var wire 3 & funct3 [2:0] $end
$var wire 7 ' funct7 [6:0] $end
$var parameter 4 ( ALU_ADD $end
$var parameter 4 ) ALU_AND $end
$var parameter 2 * ALU_OP_BRANCH $end
$var parameter 2 + ALU_OP_I_TYPE $end
$var parameter 2 , ALU_OP_OTHER $end
$var parameter 2 - ALU_OP_R_TYPE $end
$var parameter 4 . ALU_OR $end
$var parameter 4 / ALU_SLL $end
$var parameter 4 0 ALU_SLT $end
$var parameter 4 1 ALU_SRA $end
$var parameter 4 2 ALU_SRL $end
$var parameter 4 3 ALU_SUB $end
$var parameter 4 4 ALU_XOR $end
$var reg 4 5 alu_ctrl [3:0] $end
$upscope $end
$upscope $end
$enddefinitions $end
$comment Show the parameter values. $end
$dumpall
b100 4
b1 3
b111 2
b1000 1
b101 0
b110 /
b11 .
b10 -
b0 ,
b11 +
b1 *
b10 )
b0 (
$end
#0
$dumpvars
b0 5
b0 '
b0 &
b10 %
b0 $
b0 #
b10 "
b0 !
$end
#10
b1 !
b1 5
b100000 $
b100000 '
#20
b10 !
b10 5
b0 $
b0 '
b111 #
b111 &
#30
b11 !
b11 5
b110 #
b110 &
#40
b100 !
b100 5
b100 #
b100 &
#50
b101 !
b101 5
b10 #
b10 &
#60
b110 !
b110 5
b1 #
b1 &
#70
b111 !
b111 5
b101 #
b101 &
#80
b1000 !
b1000 5
b100000 $
b100000 '
#90
b0 !
b0 5
b0 $
b0 '
b0 #
b0 &
b11 "
b11 %
#100
b10 !
b10 5
b111 #
b111 &
#110
b11 !
b11 5
b110 #
b110 &
#120
b100 !
b100 5
b100 #
b100 &
#130
b101 !
b101 5
b10 #
b10 &
#140
b110 !
b110 5
b1 #
b1 &
#150
b111 !
b111 5
b101 #
b101 &
#160
b1000 !
b1000 5
b100000 $
b100000 '
#170
b1 !
b1 5
b0 $
b0 '
b0 #
b0 &
b1 "
b1 %
#180
b1 #
b1 &
#190
b101 !
b101 5
b100 #
b100 &
#200
b101 #
b101 &
#210
b110 #
b110 &
#220
b111 #
b111 &
#230
b0 !
b0 5
b0 #
b0 &
b0 "
b0 %
